[{"id":"90","symbol":"BTC","name":"Bitcoin","nameid":"bitcoin","rank":1,"price_usd":"26834.86","percent_change_24h":"-3.85","percent_change_1h":"-0.47","percent_change_7d":"-3.99","price_btc":"1.00","market_cap_usd":"517593443495.07","volume24":17666475956.079838,"volume24a":13606897884.631237,"csupply":"19288102.00","tsupply":"19288102","msupply":"21000000"},{"id":"80","symbol":"ETH","name":"Ethereum","nameid":"ethereum","rank":2,"price_usd":"1720.93","percent_change_24h":"-2.42","percent_change_1h":"-0.26","percent_change_7d":"-1.65","price_btc":"0.064059","market_cap_usd":"210597804768.48","volume24":8913707272.94157,"volume24a":6925085631.506663,"csupply":"122374074.00","tsupply":"122374074","msupply":""},{"id":"518","symbol":"USDT","name":"Tether","nameid":"tether","rank":3,"price_usd":"1.00","percent_change_24h":"0.01","percent_change_1h":"0.15","percent_change_7d":"0.15","price_btc":"0.000037","market_cap_usd":"68435368423.91","volume24":41030603526.7841,"volume24a":30913098046.020607,"csupply":"68319442037.00","tsupply":"73141766321.234","msupply":""},{"id":"2710","symbol":"BNB","name":"Binance Coin","nameid":"binance-coin","rank":4,"price_usd":"309.26","percent_change_24h":"-5.82","percent_change_1h":"-0.25","percent_change_7d":"-7.96","price_btc":"0.011512","market_cap_usd":"51585405449.03","volume24":632837759.016149,"volume24a":291365641.1419596,"csupply":"166801148.00","tsupply":"192443301","msupply":"200000000"},{"id":"33285","symbol":"USDC","name":"USD Coin","nameid":"usd-coin","rank":5,"price_usd":"0.999672","percent_change_24h":"0.05","percent_change_1h":"0.01","percent_change_7d":"0.40","price_btc":"0.000037","market_cap_usd":"41287308096.16","volume24":1451710411.1898391,"volume24a":856891043.5169519,"csupply":"41300868946.00","tsupply":"41300868946.621","msupply":""},{"id":"58","symbol":"XRP","name":"XRP","nameid":"ripple","rank":6,"price_usd":"0.482539","percent_change_24h":"3.23","percent_change_1h":"-0.02","percent_change_7d":"28.34","price_btc":"0.000018","market_cap_usd":"20705518720.46","volume24":2307153483.268733,"volume24a":1149195320.9548345,"csupply":"42909539227.00","tsupply":"99991841593","msupply":"100000000000"},{"id":"48591","symbol":"BUSD","name":"Binance USD","nameid":"binance-usd","rank":7,"price_usd":"0.999433","percent_change_24h":"-0.03","percent_change_1h":"0.03","percent_change_7d":"0.10","price_btc":"0.000037","market_cap_usd":"16139760633.82","volume24":2727390988.371289,"volume24a":1782305095.2808328,"csupply":"16148914845.00","tsupply":"16148914845.973","msupply":""},{"id":"257","symbol":"ADA","name":"Cardano","nameid":"cardano","rank":8,"price_usd":"0.347574","percent_change_24h":"-1.11","percent_change_1h":"0.30","percent_change_7d":"4.16","price_btc":"0.000013","market_cap_usd":"12033774357.55","volume24":233575602.19276643,"volume24a":183064713.31493112,"csupply":"34622161734.00","tsupply":"35467426506.415","msupply":"45000000000"},{"id":"2","symbol":"DOGE","name":"Dogecoin","nameid":"dogecoin","rank":9,"price_usd":"0.072263","percent_change_24h":"-1.95","percent_change_1h":"0.16","percent_change_7d":"0.77","price_btc":"0.000003","market_cap_usd":"9979800495.85","volume24":385527599.8640371,"volume24a":210562857.90228102,"csupply":"138103296384.00","tsupply":"138103296384","msupply":""},{"id":"48543","symbol":"SOL","name":"Solana","nameid":"solana","rank":10,"price_usd":"19.77","percent_change_24h":"-4.07","percent_change_1h":"-0.66","percent_change_7d":"-12.47","price_btc":"0.000736","market_cap_usd":"7417859339.40","volume24":392305976.50601524,"volume24a":235714076.99824926,"csupply":"375273818.00","tsupply":"491561409.22682","msupply":""},{"id":"46971","symbol":"STETH","name":"Staked Ether","nameid":"staked-ether","rank":11,"price_usd":"1636.81","percent_change_24h":"-0.47","percent_change_1h":"0.01","percent_change_7d":"0.30","price_btc":"0.060928","market_cap_usd":"7000401788.62","volume24":332676161.478569,"volume24a":317965918.36000204,"csupply":"4276864.00","tsupply":null,"msupply":null},{"id":"45219","symbol":"DOT","name":"Polkadot","nameid":"polkadot","rank":12,"price_usd":"5.86","percent_change_24h":"-2.35","percent_change_1h":"-0.12","percent_change_7d":"-4.39","price_btc":"0.000218","market_cap_usd":"6679312744.86","volume24":417603405.8356273,"volume24a":205529080.54905912,"csupply":"1140780140.00","tsupply":"1221728611.6701","msupply":"1221728611.6701"},{"id":"1","symbol":"LTC","name":"Litecoin","nameid":"litecoin","rank":13,"price_usd":"86.90","percent_change_24h":"-6.01","percent_change_1h":"-0.50","percent_change_7d":"8.19","price_btc":"0.003235","market_cap_usd":"6279070216.45","volume24":1202018650.8211014,"volume24a":713041231.2050188,"csupply":"72259441.00","tsupply":"72259441","msupply":"84000000"},{"id":"2713","symbol":"TRX","name":"TRON","nameid":"tron","rank":14,"price_usd":"0.063800","percent_change_24h":"-0.41","percent_change_1h":"-0.02","percent_change_7d":"-2.78","price_btc":"0.000002","market_cap_usd":"5848433393.87","volume24":333296421.37991107,"volume24a":276875487.77320725,"csupply":"91668462019.00","tsupply":"91668466032.099","msupply":""},{"id":"45088","symbol":"SHIB","name":"Shiba Inu","nameid":"shiba-inu","rank":15,"price_usd":"0.000010","percent_change_24h":"-1.82","percent_change_1h":"0.32","percent_change_7d":"-1.67","price_btc":"3.85E-10","market_cap_usd":"5673309031.45","volume24":226458452.17033294,"volume24a":115723176.6180875,"csupply":"549063278876300.00","tsupply":"5.8973503040832E+14","msupply":""},{"id":"44883","symbol":"AVAX","name":"Avalanche","nameid":"avalanche","rank":16,"price_usd":"16.48","percent_change_24h":"-2.25","percent_change_1h":"-0.39","percent_change_7d":"-2.21","price_btc":"0.000614","market_cap_usd":"5194626292.75","volume24":120979221.46456915,"volume24a":65599525.85275699,"csupply":"315125667.00","tsupply":"420531657.22777","msupply":"720000000"},{"id":"33422","symbol":"WBTC","name":"Wrapped Bitcoin","nameid":"wrapped-bitcoin","rank":17,"price_usd":"26920.43","percent_change_24h":"-3.65","percent_change_1h":"-0.40","percent_change_7d":"-3.67","price_btc":"1.00","market_cap_usd":"4743271333.12","volume24":4909576793.080344,"volume24a":5835079281.94961,"csupply":"176196.00","tsupply":"176196.96135694","msupply":""},{"id":"47305","symbol":"UNI","name":"Uniswap","nameid":"uniswap","rank":18,"price_usd":"5.71","percent_change_24h":"-0.86","percent_change_1h":"0.05","percent_change_7d":"-8.18","price_btc":"0.000212","market_cap_usd":"4349401032.31","volume24":48953637.15726325,"volume24a":36377202.72184091,"csupply":"762209326.00","tsupply":"1000000000","msupply":"1000000000"},{"id":"2751","symbol":"LINK","name":"ChainLink","nameid":"chainlink","rank":19,"price_usd":"6.79","percent_change_24h":"-5.17","percent_change_1h":"-0.30","percent_change_7d":"-4.87","price_btc":"0.000253","market_cap_usd":"3449375071.52","volume24":261058224.09622163,"volume24a":178250517.26451072,"csupply":"507999970.00","tsupply":"1000000000","msupply":"1000000000"},{"id":"33833","symbol":"LEO","name":"UNUS SED LEO","nameid":"unus-sed-leo","rank":20,"price_usd":"3.38","percent_change_24h":"-0.66","percent_change_1h":"0.08","percent_change_7d":"0.66","price_btc":"0.000126","market_cap_usd":"3220857284.61","volume24":1540648.4125951012,"volume24a":1844466.7302887181,"csupply":"953954130.00","tsupply":"985239504","msupply":""},{"id":"33830","symbol":"ATOM","name":"Cosmos","nameid":"cosmos","rank":21,"price_usd":"10.93","percent_change_24h":"-1.73","percent_change_1h":"-0.08","percent_change_7d":"-6.06","price_btc":"0.000407","market_cap_usd":"3129646074.40","volume24":121955028.73686072,"volume24a":79381273.22339773,"csupply":"286370297.00","tsupply":"286370297","msupply":""},{"id":"77729","symbol":"TON","name":"The Open Network","nameid":"the-open-network","rank":22,"price_usd":"2.06","percent_change_24h":"-4.02","percent_change_1h":"-0.34","percent_change_7d":"-13.75","price_btc":"0.000077","market_cap_usd":"3039014539.60","volume24":9811326.975429907,"volume24a":12424095.705349747,"csupply":"1473591410.00","tsupply":"5057362773.9969","msupply":"5057362773.9969"},{"id":"28","symbol":"XMR","name":"Monero","nameid":"monero","rank":23,"price_usd":"154.74","percent_change_24h":"-4.51","percent_change_1h":"0.65","percent_change_7d":"1.55","price_btc":"0.005760","market_cap_usd":"2822243592.40","volume24":714494511.4147878,"volume24a":410948453.2271949,"csupply":"18239161.00","tsupply":"18239161.526205","msupply":""},{"id":"118","symbol":"ETC","name":"Ethereum Classic","nameid":"ethereum-classic","rank":24,"price_usd":"19.83","percent_change_24h":"-0.76","percent_change_1h":"-0.29","percent_change_7d":"0.22","price_btc":"0.000738","market_cap_usd":"2760860346.46","volume24":362985947.3304568,"volume24a":268388790.1403756,"csupply":"139232880.00","tsupply":"210700000","msupply":"210700000"},{"id":"33531","symbol":"OKB","name":"OKB","nameid":"okb","rank":25,"price_usd":"42.96","percent_change_24h":"-0.36","percent_change_1h":"-0.52","percent_change_7d":"-5.67","price_btc":"0.001599","market_cap_usd":"2577899114.70","volume24":40017580.4188049,"volume24a":31569378.720686626,"csupply":"60000000.00","tsupply":"300000000","msupply":""},{"id":"89","symbol":"XLM","name":"Stellar","nameid":"stellar","rank":26,"price_usd":"0.092615","percent_change_24h":"0.13","percent_change_1h":"-0.02","percent_change_7d":"6.53","price_btc":"0.000003","market_cap_usd":"2438738760.08","volume24":200441346.31600314,"volume24a":81730301.5461961,"csupply":"26332091529.00","tsupply":"104303927518","msupply":"104303927518"},{"id":"2321","symbol":"BCH","name":"Bitcoin Cash","nameid":"bitcoin-cash","rank":27,"price_usd":"120.16","percent_change_24h":"-2.04","percent_change_1h":"-0.15","percent_change_7d":"-8.39","price_btc":"0.004473","market_cap_usd":"2320271701.47","volume24":227166068.36159983,"volume24a":202557710.67926162,"csupply":"19309281.00","tsupply":"19309281","msupply":"21000000"},{"id":"33536","symbol":"MATIC","name":"Matic Network","nameid":"matic-network","rank":28,"price_usd":"1.05","percent_change_24h":"-3.13","percent_change_1h":"-0.12","percent_change_7d":"-6.04","price_btc":"0.000039","market_cap_usd":"2278178334.79","volume24":320007874.5582022,"volume24a":233935173.82503948,"csupply":"2175190262.00","tsupply":"10000000000","msupply":""},{"id":"32607","symbol":"FIL","name":"Filecoin","nameid":"filecoin","rank":29,"price_usd":"5.36","percent_change_24h":"-3.35","percent_change_1h":"-0.01","percent_change_7d":"-6.91","price_btc":"0.000200","market_cap_usd":"2089040015.28","volume24":199260803.6749407,"volume24a":150087451.54771745,"csupply":"389513726.00","tsupply":"389513726","msupply":""},{"id":"46981","symbol":"LDO","name":"Lido DAO","nameid":"lido-dao","rank":30,"price_usd":"2.06","percent_change_24h":"-5.38","percent_change_1h":"0.12","percent_change_7d":"-10.96","price_btc":"0.000077","market_cap_usd":"1738600060.85","volume24":456777181.19089764,"volume24a":410801599.5661194,"csupply":"842566596.00","tsupply":"1000000000","msupply":"1000000000"},{"id":"2741","symbol":"VET","name":"VeChain","nameid":"vechain","rank":31,"price_usd":"0.021733","percent_change_24h":"-3.94","percent_change_1h":"-0.09","percent_change_7d":"-6.46","price_btc":"8.09E-7","market_cap_usd":"1575892362.64","volume24":69976932.57171102,"volume24a":33595546.590895094,"csupply":"72511146418.00","tsupply":"85985041177","msupply":"86712634466"},{"id":"48563","symbol":"NEAR","name":"NEAR Protocol","nameid":"near-protocol","rank":32,"price_usd":"1.83","percent_change_24h":"-5.09","percent_change_1h":"-0.52","percent_change_7d":"-8.82","price_btc":"0.000068","market_cap_usd":"1563475562.92","volume24":71817685.21317342,"volume24a":47571365.56614773,"csupply":"852573235.00","tsupply":"1000000000","msupply":"1000000000"},{"id":"33085","symbol":"QNT","name":"Quant","nameid":"quant","rank":33,"price_usd":"119.02","percent_change_24h":"-3.23","percent_change_1h":"-0.08","percent_change_7d":"-7.32","price_btc":"0.004430","market_cap_usd":"1436916664.35","volume24":23644855.764353827,"volume24a":14342952.200678593,"csupply":"12072738.00","tsupply":"14612493.080826","msupply":"14612493"},{"id":"34406","symbol":"ALGO","name":"Algorand","nameid":"algorand","rank":34,"price_usd":"0.198395","percent_change_24h":"-3.78","percent_change_1h":"-0.62","percent_change_7d":"-5.59","price_btc":"0.000007","market_cap_usd":"1423774694.44","volume24":49439072.78714234,"volume24a":28320550.493680313,"csupply":"7176451411.00","tsupply":"7398649569.7265","msupply":"10000000000"},{"id":"45930","symbol":"APE","name":"APEcoin","nameid":"apecoin","rank":35,"price_usd":"4.08","percent_change_24h":"1.79","percent_change_1h":"-0.07","percent_change_7d":"0.08","price_btc":"0.000152","market_cap_usd":"1253457898.64","volume24":148933123.3792424,"volume24a":84200750.77985267,"csupply":"306875000.00","tsupply":"10000000","msupply":"10000000"},{"id":"2679","symbol":"EOS","name":"EOS","nameid":"eos","rank":36,"price_usd":"1.10","percent_change_24h":"-2.41","percent_change_1h":"-0.34","percent_change_7d":"-7.16","price_btc":"0.000041","market_cap_usd":"1184559803.79","volume24":167112568.09355637,"volume24a":88539276.16491722,"csupply":"1081263745.00","tsupply":"1082442140.5364","msupply":""},{"id":"48569","symbol":"STX","name":"Stacks","nameid":"stacks","rank":37,"price_usd":"0.869978","percent_change_24h":"-8.79","percent_change_1h":"-0.80","percent_change_7d":"-25.90","price_btc":"0.000032","market_cap_usd":"1183169203.83","volume24":135566659.82365456,"volume24a":152325606.9850428,"csupply":"1359998486.00","tsupply":"1352464600","msupply":"1818000000"},{"id":"48561","symbol":"GRT","name":"The Graph","nameid":"the-graph","rank":38,"price_usd":"0.130581","percent_change_24h":"-5.98","percent_change_1h":"-0.82","percent_change_7d":"-12.52","price_btc":"0.000005","market_cap_usd":"1147197807.67","volume24":142205328.41431627,"volume24a":85722368.16811284,"csupply":"8785330628.00","tsupply":"10582173746.816","msupply":"10556361679"},{"id":"33644","symbol":"FTM","name":"Fantom","nameid":"fantom","rank":39,"price_usd":"0.400416","percent_change_24h":"-8.29","percent_change_1h":"-0.65","percent_change_7d":"-12.35","price_btc":"0.000015","market_cap_usd":"1111827735.56","volume24":225485330.09752053,"volume24a":172212790.93230736,"csupply":"2776684253.00","tsupply":"3175000000","msupply":"3175000000"},{"id":"258","symbol":"MANA","name":"Decentraland","nameid":"decentraland","rank":40,"price_usd":"0.558162","percent_change_24h":"-3.67","percent_change_1h":"-0.35","percent_change_7d":"-7.28","price_btc":"0.000021","market_cap_usd":"1035438234.22","volume24":63103189.49675492,"volume24a":45356508.2000095,"csupply":"1855084191.00","tsupply":"2193539027.3201","msupply":""},{"id":"46968","symbol":"FRAX","name":"Frax","nameid":"frax","rank":41,"price_usd":"0.998064","percent_change_24h":"0.07","percent_change_1h":"0.04","percent_change_7d":"0.22","price_btc":"0.000037","market_cap_usd":"1022370287.16","volume24":5849322.083351677,"volume24a":1019872.6902314627,"csupply":"1024353133.00","tsupply":"1024353133.2588","msupply":""},{"id":"3682","symbol":"XTZ","name":"Tezos","nameid":"tezos","rank":42,"price_usd":"1.08","percent_change_24h":"-3.76","percent_change_1h":"-0.40","percent_change_7d":"-8.25","price_btc":"0.000040","market_cap_usd":"1000411427.98","volume24":33470286.283649348,"volume24a":28755509.646727905,"csupply":"926661394.00","tsupply":"948074271.2703","msupply":""},{"id":"44036","symbol":"CUSDC","name":"Compound USD Coin","nameid":"compound-usd-coin","rank":43,"price_usd":"0.022285","percent_change_24h":"-1.19","percent_change_1h":"-0.13","percent_change_7d":"-2.02","price_btc":"8.30E-7","market_cap_usd":"993115475.50","volume24":4691664.3326997915,"volume24a":1538810.5030407712,"csupply":"44564678457.00","tsupply":"9803299805.0364","msupply":""},{"id":"46018","symbol":"AAVE","name":"Aave","nameid":"aave","rank":44,"price_usd":"69.42","percent_change_24h":"-3.57","percent_change_1h":"-0.51","percent_change_7d":"-9.55","price_btc":"0.002584","market_cap_usd":"978410263.40","volume24":222519792.63757232,"volume24a":135118557.48872787,"csupply":"14093192.00","tsupply":"16000000","msupply":"16000000"},{"id":"32360","symbol":"THETA","name":"Theta Token","nameid":"theta-token","rank":45,"price_usd":"0.968014","percent_change_24h":"-2.22","percent_change_1h":"-0.23","percent_change_7d":"-5.09","price_btc":"0.000036","market_cap_usd":"968013539.95","volume24":61281456.903546765,"volume24a":30769031.624507915,"csupply":"1000000000.00","tsupply":"1000000000","msupply":null},{"id":"32479","symbol":"TUSD","name":"TrueUSD","nameid":"trueusd","rank":46,"price_usd":"0.997761","percent_change_24h":"0.04","percent_change_1h":"0.08","percent_change_7d":"0.03","price_btc":"0.000037","market_cap_usd":"944515345.31","volume24":499917385.97874427,"volume24a":315029944.1875319,"csupply":"946634804.00","tsupply":"946634804.97095","msupply":""},{"id":"48589","symbol":"FLOW","name":"Flow","nameid":"flow","rank":47,"price_usd":"0.909105","percent_change_24h":"-3.97","percent_change_1h":"-0.13","percent_change_7d":"-12.31","price_btc":"0.000034","market_cap_usd":"942014593.06","volume24":23842756.7858311,"volume24a":12805894.270133235,"csupply":"1036200000.00","tsupply":"1414011748","msupply":""},{"id":"45161","symbol":"SAND","name":"The Sandbox","nameid":"the-sandbox","rank":48,"price_usd":"0.596382","percent_change_24h":"-2.78","percent_change_1h":"0.03","percent_change_7d":"-10.40","price_btc":"0.000022","market_cap_usd":"894256662.15","volume24":132713478.72829585,"volume24a":71217942.5179167,"csupply":"1499470108.00","tsupply":"3000000000","msupply":"3000000000"},{"id":"64671","symbol":"USDP","name":"Pax Dollar","nameid":"pax-dollar","rank":49,"price_usd":"0.999436","percent_change_24h":"0.07","percent_change_1h":"-0.03","percent_change_7d":"0.20","price_btc":"0.000037","market_cap_usd":"859783911.27","volume24":8556875.535063788,"volume24a":2445379.673964034,"csupply":"860268741.00","tsupply":null,"msupply":null},{"id":"43123","symbol":"CETH","name":"Compound Ether","nameid":"compound-ether","rank":50,"price_usd":"33.95","percent_change_24h":"-2.42","percent_change_1h":"-0.27","percent_change_7d":"1.01","price_btc":"0.001264","market_cap_usd":"855677528.83","volume24":10455493.924414009,"volume24a":477276.74537743494,"csupply":"25207543.00","tsupply":"41649823","msupply":""},{"id":"133","symbol":"NEO","name":"Neo","nameid":"neo","rank":51,"price_usd":"12.10","percent_change_24h":"-4.67","percent_change_1h":"-0.22","percent_change_7d":"-2.57","price_btc":"0.000450","market_cap_usd":"853316734.09","volume24":272087609.26506317,"volume24a":193999250.323397,"csupply":"70538831.00","tsupply":"100000000","msupply":"100000000"},{"id":"44034","symbol":"CDAI","name":"Compound Dai","nameid":"compound-dai","rank":52,"price_usd":"0.022207","percent_change_24h":"3.23","percent_change_1h":"-0.13","percent_change_7d":"0.38","price_btc":"8.27E-7","market_cap_usd":"835689153.94","volume24":9724561.331043644,"volume24a":21010873.746685334,"csupply":"37631506011.00","tsupply":"2025596474","msupply":""},{"id":"32893","symbol":"PHB","name":"Red Pulse Phoenix","nameid":"red-pulse","rank":53,"price_usd":"0.984413","percent_change_24h":"-6.58","percent_change_1h":"-0.03","percent_change_7d":"-10.30","price_btc":"0.000037","market_cap_usd":"816658209.02","volume24":931696.3272180234,"volume24a":863390.3135750096,"csupply":"829588687.00","tsupply":"1362278592","msupply":""},{"id":"46575","symbol":"AXS","name":"Axie Infinity","nameid":"axie-infinity","rank":54,"price_usd":"8.03","percent_change_24h":"-2.47","percent_change_1h":"0.02","percent_change_7d":"-7.85","price_btc":"0.000299","market_cap_usd":"810565704.61","volume24":175242719.36902332,"volume24a":102232098.38336004,"csupply":"100910035.00","tsupply":"270000000","msupply":"270000000"},{"id":"34391","symbol":"CHZ","name":"Chiliz","nameid":"chiliz","rank":55,"price_usd":"0.113984","percent_change_24h":"-4.21","percent_change_1h":"0.25","percent_change_7d":"-3.76","price_btc":"0.000004","market_cap_usd":"759533261.52","volume24":46184086.65018071,"volume24a":23370444.499505278,"csupply":"6663503543.00","tsupply":"8888888888","msupply":"8888888888"},{"id":"69801","symbol":"USDD","name":"USDD","nameid":"usdd","rank":56,"price_usd":"0.988713","percent_change_24h":"-0.04","percent_change_1h":"0.06","percent_change_7d":"-0.31","price_btc":"0.000037","market_cap_usd":"717145339.63","volume24":7912568.63182853,"volume24a":5136630.621025525,"csupply":"725332035.00","tsupply":"798144027","msupply":""},{"id":"48537","symbol":"LUNC","name":"Terra Classic","nameid":"terra-luna","rank":57,"price_usd":"0.000120","percent_change_24h":"-3.40","percent_change_1h":"-0.46","percent_change_7d":"-6.18","price_btc":"4.46E-9","market_cap_usd":"709070577.94","volume24":21602696.6656404,"volume24a":19021541.033355303,"csupply":"5924247387375.00","tsupply":"6576804998885.5","msupply":"6576804998885.5"},{"id":"42531","symbol":"KLAY","name":"Klaytn","nameid":"klaytn","rank":58,"price_usd":"0.221743","percent_change_24h":"-3.31","percent_change_1h":"-0.63","percent_change_7d":"-2.51","price_btc":"0.000008","market_cap_usd":"686455697.59","volume24":21069147.58973236,"volume24a":13570133.29896946,"csupply":"3095731717.00","tsupply":"11021438731.797","msupply":""},{"id":"33234","symbol":"BCHSV","name":"Bitcoin SV","nameid":"bitcoin-cash-sv","rank":59,"price_usd":"35.16","percent_change_24h":"-2.94","percent_change_1h":"-0.25","percent_change_7d":"-2.85","price_btc":"0.001309","market_cap_usd":"677433636.72","volume24":81148571.39943925,"volume24a":84360313.62874953,"csupply":"19266077.00","tsupply":"21000000","msupply":"21000000"},{"id":"12377","symbol":"MKR","name":"Maker","nameid":"maker","rank":60,"price_usd":"681.79","percent_change_24h":"1.73","percent_change_1h":"-0.60","percent_change_7d":"0.82","price_btc":"0.025379","market_cap_usd":"666538429.39","volume24":712300961.8436584,"volume24a":341351822.2756299,"csupply":"977631.00","tsupply":"977631.03695089","msupply":"1005577"},{"id":"48581","symbol":"CRV","name":"Curve DAO Token","nameid":"curve-dao-token","rank":61,"price_usd":"0.888267","percent_change_24h":"-3.85","percent_change_1h":"-0.10","percent_change_7d":"-8.32","price_btc":"0.000033","market_cap_usd":"645722017.88","volume24":32883098.392664798,"volume24a":26383997.35817663,"csupply":"726945497.00","tsupply":"1899889263.5002","msupply":"3303030299"},{"id":"77735","symbol":"GMX","name":"GMX","nameid":"gmx","rank":62,"price_usd":"72.66","percent_change_24h":"6.31","percent_change_1h":"-0.06","percent_change_7d":"-10.28","price_btc":"0.002704","market_cap_usd":"614606965.44","volume24":70212326.95144601,"volume24a":29260964.03301371,"csupply":"8459230.00","tsupply":"8872813.6496366","msupply":""},{"id":"8","symbol":"DASH","name":"Dash","nameid":"dash","rank":63,"price_usd":"55.14","percent_change_24h":"-4.24","percent_change_1h":"-0.44","percent_change_7d":"-1.66","price_btc":"0.002052","market_cap_usd":"614120970.17","volume24":100384717.86409408,"volume24a":92514004.67578055,"csupply":"11138031.00","tsupply":"11138031","msupply":"18900000"},{"id":"33819","symbol":"CRO","name":"Crypto.com Chain","nameid":"crypto-com-chain","rank":64,"price_usd":"0.066081","percent_change_24h":"-2.76","percent_change_1h":"-1.01","percent_change_7d":"-7.61","price_btc":"0.000002","market_cap_usd":"613284907.71","volume24":6141096.114109702,"volume24a":3741614.4120028364,"csupply":"9280821918.00","tsupply":"100000000000","msupply":""},{"id":"45985","symbol":"CAKE","name":"PancakeSwap","nameid":"pancakeswap","rank":65,"price_usd":"3.57","percent_change_24h":"-4.45","percent_change_1h":"-0.12","percent_change_7d":"-6.51","price_btc":"0.000133","market_cap_usd":"606760275.17","volume24":90786479.52616133,"volume24a":138583814.97154623,"csupply":"170044393.00","tsupply":"370361115.53566","msupply":"750000000"},{"id":"134","symbol":"ZEC","name":"Zcash","nameid":"zcash","rank":66,"price_usd":"35.86","percent_change_24h":"0.77","percent_change_1h":"-0.56","percent_change_7d":"3.44","price_btc":"0.001335","market_cap_usd":"585454269.35","volume24":205328431.43688825,"volume24a":80385070.86711085,"csupply":"16328269.00","tsupply":"16328269","msupply":"21000000"},{"id":"32351","symbol":"HT","name":"Huobi Token","nameid":"huobi-token","rank":67,"price_usd":"3.58","percent_change_24h":"-1.75","percent_change_1h":"-1.55","percent_change_7d":"-10.63","price_btc":"0.000133","market_cap_usd":"580405527.99","volume24":7400895.281640195,"volume24a":6373866.812222712,"csupply":"162233844.00","tsupply":"203980445","msupply":"500000000"},{"id":"48555","symbol":"HBAR","name":"Hedera Hashgraph","nameid":"hedera-hashgraph","rank":68,"price_usd":"0.059331","percent_change_24h":"-2.35","percent_change_1h":"0.37","percent_change_7d":"-3.89","price_btc":"0.000002","market_cap_usd":"571571419.96","volume24":50737097.379507,"volume24a":36365715.92499762,"csupply":"9633530220.00","tsupply":"50000000000","msupply":"50000000000"},{"id":"51539","symbol":"XEC","name":"eCash","nameid":"ecash","rank":69,"price_usd":"0.000029","percent_change_24h":"-3.14","percent_change_1h":"-0.55","percent_change_7d":"-7.89","price_btc":"1.08E-9","market_cap_usd":"562290872.12","volume24":5009098.629888959,"volume24a":3946532.1845063665,"csupply":"19305535923303.00","tsupply":"19141067173303","msupply":"21000000000000"},{"id":"447","symbol":"MIOTA","name":"IOTA","nameid":"iota","rank":70,"price_usd":"0.199965","percent_change_24h":"-2.62","percent_change_1h":"-0.16","percent_change_7d":"-6.92","price_btc":"0.000007","market_cap_usd":"555807721.77","volume24":7242956.701866895,"volume24a":5681160.39323212,"csupply":"2779530283.00","tsupply":"2779530283","msupply":"2779530283"},{"id":"45467","symbol":"EGLD","name":"Elrond eGold","nameid":"elrond-egold","rank":71,"price_usd":"41.02","percent_change_24h":"-2.62","percent_change_1h":"0.23","percent_change_7d":"-11.48","price_btc":"0.001527","market_cap_usd":"554090600.28","volume24":35354805.81866146,"volume24a":13427946.872177964,"csupply":"13508333.00","tsupply":"20000000","msupply":null},{"id":"42227","symbol":"PAXG","name":"PAX Gold","nameid":"pax-gold","rank":72,"price_usd":"1974.47","percent_change_24h":"-0.10","percent_change_1h":"-0.05","percent_change_7d":"-0.17","price_btc":"0.073497","market_cap_usd":"535600695.28","volume24":804285566.0652418,"volume24a":814945812.0508363,"csupply":"271263.00","tsupply":"271263.71","msupply":""},{"id":"44035","symbol":"TKX","name":"Tokenize Xchange","nameid":"tokenize-xchange","rank":73,"price_usd":"6.09","percent_change_24h":"-1.81","percent_change_1h":"-0.20","percent_change_7d":"-3.47","price_btc":"0.000227","market_cap_usd":"487166232.22","volume24":8681788.986998271,"volume24a":8335963.304573869,"csupply":"79996000.00","tsupply":"100000000","msupply":""},{"id":"42855","symbol":"XAUT","name":"Tether Gold","nameid":"tether-gold","rank":74,"price_usd":"1959.72","percent_change_24h":"-0.44","percent_change_1h":"0.10","percent_change_7d":"-0.98","price_btc":"0.072948","market_cap_usd":"483116856.99","volume24":6741582.372148156,"volume24a":6298409.057401608,"csupply":"246524.00","tsupply":"246524","msupply":""},{"id":"32354","symbol":"AGIX","name":"SingularityNET","nameid":"singularitynet","rank":75,"price_usd":"0.393998","percent_change_24h":"-7.01","percent_change_1h":"-0.27","percent_change_7d":"-14.27","price_btc":"0.000015","market_cap_usd":"474421150.30","volume24":118976417.64336573,"volume24a":100565833.99147733,"csupply":"1204121857.00","tsupply":"1260840661.7364","msupply":"2000000000"},{"id":"84965","symbol":"FLR","name":"Flare","nameid":"flare","rank":76,"price_usd":"0.042291","percent_change_24h":"23.84","percent_change_1h":"-2.83","percent_change_7d":"39.89","price_btc":"0.000002","market_cap_usd":"470293814.22","volume24":48788602.09666702,"volume24a":6602338.751507407,"csupply":"11120335746.00","tsupply":"100559787198","msupply":""},{"id":"44178","symbol":"TWT","name":"Trust Wallet Token","nameid":"trust-wallet-token","rank":77,"price_usd":"1.11","percent_change_24h":"-6.17","percent_change_1h":"-0.58","percent_change_7d":"-8.46","price_btc":"0.000041","market_cap_usd":"462767540.03","volume24":23978484.992344096,"volume24a":9438540.716025013,"csupply":"416649900.00","tsupply":"999668148","msupply":"1000000000"},{"id":"2781","symbol":"LRC","name":"Loopring","nameid":"loopring","rank":78,"price_usd":"0.335940","percent_change_24h":"-3.85","percent_change_1h":"0.15","percent_change_7d":"-3.07","price_btc":"0.000013","market_cap_usd":"446845364.93","volume24":38251049.251521654,"volume24a":43530226.38829265,"csupply":"1330133545.00","tsupply":"1373873437.4425","msupply":"1374513896"},{"id":"70497","symbol":"OP","name":"Optimism","nameid":"optimism","rank":79,"price_usd":"2.06","percent_change_24h":"-6.42","percent_change_1h":"0.27","percent_change_7d":"-17.93","price_btc":"0.000077","market_cap_usd":"442513521.93","volume24":678066818.0691926,"volume24a":404407467.5759647,"csupply":"214748364.00","tsupply":"4294967296","msupply":"4294967296"},{"id":"48547","symbol":"FTT","name":"FTX Token","nameid":"ftx-token","rank":80,"price_usd":"1.33","percent_change_24h":"4.41","percent_change_1h":"-0.23","percent_change_7d":"-4.14","price_btc":"0.000049","market_cap_usd":"437318748.34","volume24":6054894.762209563,"volume24a":3983198.2563007087,"csupply":"328895103.00","tsupply":"328895103.81321","msupply":"352170015"},{"id":"36447","symbol":"RUNE","name":"THORChain","nameid":"thorchain","rank":81,"price_usd":"1.32","percent_change_24h":"-5.43","percent_change_1h":"-0.26","percent_change_7d":"-7.02","price_btc":"0.000049","market_cap_usd":"430124104.19","volume24":14848831.71318454,"volume24a":8932061.094154976,"csupply":"327056566.00","tsupply":"498910727","msupply":"500000000"},{"id":"33213","symbol":"RPL","name":"Rocket Pool","nameid":"rocket-pool","rank":82,"price_usd":"41.24","percent_change_24h":"0.07","percent_change_1h":"0.32","percent_change_7d":"1.57","price_btc":"0.001535","market_cap_usd":"423958279.20","volume24":32584439.810392667,"volume24a":15669214.589371333,"csupply":"10279742.00","tsupply":"18970871","msupply":"18970871"},{"id":"62645","symbol":"MINA","name":"Mina Protocol","nameid":"mina-protocol","rank":83,"price_usd":"0.714533","percent_change_24h":"-9.76","percent_change_1h":"-1.09","percent_change_7d":"-11.19","price_btc":"0.000027","market_cap_usd":"420514905.51","volume24":42830740.55091498,"volume24a":26084543.1973185,"csupply":"588516938.00","tsupply":"944454412.84004","msupply":"944454412.84004"},{"id":"32334","symbol":"ZIL","name":"Zilliqa","nameid":"zilliqa","rank":84,"price_usd":"0.025900","percent_change_24h":"-3.88","percent_change_1h":"-0.20","percent_change_7d":"-7.01","price_btc":"9.64E-7","market_cap_usd":"410979231.67","volume24":44124387.73068899,"volume24a":21045459.14349434,"csupply":"15867699446.00","tsupply":"17170501052.575","msupply":"21000000000"},{"id":"32604","symbol":"NEXO","name":"Nexo","nameid":"nexo","rank":85,"price_usd":"0.711577","percent_change_24h":"-5.12","percent_change_1h":"0.72","percent_change_7d":"-1.06","price_btc":"0.000026","market_cap_usd":"398483141.19","volume24":4647175.896695408,"volume24a":5346885.277612911,"csupply":"560000011.00","tsupply":"1000000000","msupply":"1000000000"},{"id":"46966","symbol":"1INCH","name":"1inch","nameid":"1inch","rank":86,"price_usd":"0.490977","percent_change_24h":"-2.85","percent_change_1h":"0.24","percent_change_7d":"-6.72","price_btc":"0.000018","market_cap_usd":"389030052.03","volume24":64806853.72274946,"volume24a":30798545.645044018,"csupply":"792358384.00","tsupply":"1500000000","msupply":""},{"id":"64739","symbol":"BTSE","name":"BTSE Token","nameid":"btse-token","rank":87,"price_usd":"2.40","percent_change_24h":"1.74","percent_change_1h":"0.38","percent_change_7d":"2.26","price_btc":"0.000089","market_cap_usd":"388299356.40","volume24":736842.9330040233,"volume24a":561328.7093831819,"csupply":"162061501.00","tsupply":"200000000","msupply":"200000000"},{"id":"64669","symbol":"OSMO","name":"Osmosis","nameid":"osmosis","rank":88,"price_usd":"0.779557","percent_change_24h":"-2.36","percent_change_1h":"-0.43","percent_change_7d":"-4.76","price_btc":"0.000029","market_cap_usd":"384002654.27","volume24":3910411.7470055004,"volume24a":2891442.79045122,"csupply":"492590761.00","tsupply":"325000000","msupply":"1000000000"},{"id":"47375","symbol":"MASK","name":"Mask Network","nameid":"mask-network","rank":89,"price_usd":"5.52","percent_change_24h":"-8.77","percent_change_1h":"0.10","percent_change_7d":"-2.74","price_btc":"0.000206","market_cap_usd":"376584241.85","volume24":247974639.35946003,"volume24a":309035207.0298322,"csupply":"68200000.00","tsupply":"100000000","msupply":"100000000"},{"id":"59967","symbol":"FEI","name":"Fei USD","nameid":"fei-usd","rank":90,"price_usd":"0.876900","percent_change_24h":"1.94","percent_change_1h":"1.65","percent_change_7d":"17.75","price_btc":"0.000033","market_cap_usd":"372679147.61","volume24":1296439.5769492942,"volume24a":1098519.18012906,"csupply":"424996177.00","tsupply":"426116732.69177","msupply":""},{"id":"70485","symbol":"KAS","name":"Kaspa","nameid":"kaspa","rank":91,"price_usd":"0.022403","percent_change_24h":"15.87","percent_change_1h":"-3.30","percent_change_7d":"34.39","price_btc":"8.34E-7","market_cap_usd":"371473623.19","volume24":16517884.54951748,"volume24a":9146630.841365686,"csupply":"16581327191.00","tsupply":"16581327191","msupply":"28704026601"},{"id":"54377","symbol":"DYDX","name":"dYdX","nameid":"dydx","rank":92,"price_usd":"2.36","percent_change_24h":"1.40","percent_change_1h":"0.01","percent_change_7d":"-6.10","price_btc":"0.000088","market_cap_usd":"368986275.00","volume24":192744844.34953114,"volume24a":103343440.80245824,"csupply":"156256174.00","tsupply":"1000000000","msupply":"1000000000"},{"id":"48829","symbol":"CVX","name":"Convex Finance","nameid":"convex-finance","rank":93,"price_usd":"4.95","percent_change_24h":"-2.49","percent_change_1h":"-0.40","percent_change_7d":"-9.32","price_btc":"0.000184","market_cap_usd":"368728713.01","volume24":2106610.6704936232,"volume24a":1911795.312646051,"csupply":"74512928.00","tsupply":"97320061.556099","msupply":"100000000"},{"id":"2581","symbol":"ENJ","name":"Enjin Coin","nameid":"enjin-coin","rank":94,"price_usd":"0.363714","percent_change_24h":"-4.77","percent_change_1h":"-0.26","percent_change_7d":"-9.68","price_btc":"0.000014","market_cap_usd":"363714260.22","volume24":34679031.739206895,"volume24a":18828464.65222938,"csupply":"1000000000.00","tsupply":"1000000000","msupply":"1000000000"},{"id":"48703","symbol":"CSPR","name":"Casper","nameid":"casper","rank":95,"price_usd":"0.033354","percent_change_24h":"-4.61","percent_change_1h":"-0.33","percent_change_7d":"-7.66","price_btc":"0.000001","market_cap_usd":"358279503.99","volume24":3988090.1962944292,"volume24a":3918701.807551973,"csupply":"10741824344.00","tsupply":"11071639958","msupply":""},{"id":"77733","symbol":"ETHW","name":"EthereumPoW","nameid":"ethereumpow","rank":96,"price_usd":"3.31","percent_change_24h":"-1.03","percent_change_1h":"0.32","percent_change_7d":"-0.60","price_btc":"0.000123","market_cap_usd":"355624174.11","volume24":6054978.737183718,"volume24a":4999244.170033928,"csupply":"107376569.00","tsupply":"107376651.04993","msupply":"107376651.04993"},{"id":"184","symbol":"BAT","name":"Basic Attention Token","nameid":"basic-attention-token","rank":97,"price_usd":"0.236463","percent_change_24h":"-0.53","percent_change_1h":"-0.41","percent_change_7d":"-5.04","price_btc":"0.000009","market_cap_usd":"353476178.04","volume24":81610563.13685417,"volume24a":57728870.34329782,"csupply":"1494845201.00","tsupply":"1500000000","msupply":"1500000000"},{"id":"56145","symbol":"SSV","name":"SSV Network","nameid":"ssv-network","rank":98,"price_usd":"35.04","percent_change_24h":"-6.51","percent_change_1h":"-2.85","percent_change_7d":"-5.53","price_btc":"0.001304","market_cap_usd":"350402788.69","volume24":93475065.87840734,"volume24a":75029627.17066249,"csupply":"10000000.00","tsupply":"11076871","msupply":""},{"id":"64675","symbol":"KAVA","name":"Kava","nameid":"kava","rank":99,"price_usd":"0.843930","percent_change_24h":"-1.10","percent_change_1h":"0.56","percent_change_7d":"-10.08","price_btc":"0.000031","market_cap_usd":"343813769.79","volume24":21681195.105487898,"volume24a":13389211.759009494,"csupply":"407395953.00","tsupply":"382198521","msupply":""},{"id":"70","symbol":"XEM","name":"NEM","nameid":"nem","rank":100,"price_usd":"0.037010","percent_change_24h":"-3.37","percent_change_1h":"-0.24","percent_change_7d":"-4.82","price_btc":"0.000001","market_cap_usd":"333088333.11","volume24":9745532.335690137,"volume24a":8549010.10066282,"csupply":"8999999999.00","tsupply":"8999999999","msupply":"8999999999"}]
